abstract_pdfs/AbstractPDFManager.py
abstract_pdfs/SliceManager.py
abstract_pdfs/__init__.py
abstract_pdfs/imports/__init__.py
abstract_pdfs/imports/imports.py
abstract_pdfs/imports/manifest_utils.py
abstract_pdfs/pdf_utils/__init__.py
abstract_pdfs/pdf_utils/imports.py
abstract_pdfs/pdf_utils/pdf_to_text.py
abstract_pdfs/pdf_utils/pdf_tools.py
abstract_pdfs-0.0.4.dist-info/METADATA
abstract_pdfs-0.0.4.dist-info/WHEEL
abstract_pdfs-0.0.4.dist-info/top_level.txt
abstract_pdfs-0.0.4.dist-info/RECORD
