Metadata-Version: 2.4
Name: abstract_pdfs
Version: 0.0.4
Summary: A modular OCR and PDF-processing toolkit for automated text extraction, deduplication, and multi-engine column-aware OCR using Tesseract, EasyOCR, and PaddleOCR
Home-page: https://github.com/AbstractEndeavors/abstract_pdfs
Author: putkoff
Author-email: partners@abstractendeavors.com
License: MIT
Classifier: Development Status :: 3 - Alpha
Classifier: Intended Audience :: Developers
Classifier: License :: OSI Approved :: MIT License
Classifier: Programming Language :: Python :: 3
Classifier: Programming Language :: Python :: 3.11
Requires-Python: >=3.6
Requires-Dist: abstract_ocr
Requires-Dist: abstract_utilities
Dynamic: author
Dynamic: author-email
Dynamic: classifier
Dynamic: description
Dynamic: description-content-type
Dynamic: home-page
Dynamic: requires-dist
Dynamic: requires-python
Dynamic: summary
